swaggerpetstore/__init__.py
swaggerpetstore/api_helper.py
swaggerpetstore/configuration.py
swaggerpetstore/swaggerpetstore_client.py
swaggerpetstore/controllers/__init__.py
swaggerpetstore/controllers/base_controller.py
swaggerpetstore/controllers/pet_controller.py
swaggerpetstore/controllers/store_controller.py
swaggerpetstore/controllers/user_controller.py
swaggerpetstore/exceptions/__init__.py
swaggerpetstore/exceptions/api_exception.py
swaggerpetstore/http/__init__.py
swaggerpetstore/http/http_call_back.py
swaggerpetstore/http/http_method_enum.py
swaggerpetstore/http/http_request.py
swaggerpetstore/http/http_response.py
swaggerpetstore/http/auth/__init__.py
swaggerpetstore/http/auth/custom_authentication.py
swaggerpetstore/models/__init__.py
swaggerpetstore/models/api_response.py
swaggerpetstore/models/category.py
swaggerpetstore/models/order.py
swaggerpetstore/models/pet.py
swaggerpetstore/models/status_1_enum.py
swaggerpetstore/models/status_2_enum.py
swaggerpetstore/models/status_enum.py
swaggerpetstore/models/tag.py
swaggerpetstore/models/user.py
swaggerpetstore/utilities/__init__.py
swaggerpetstore/utilities/file_wrapper.py
rain_pack_sdk-3.2.12.dist-info/LICENSE
rain_pack_sdk-3.2.12.dist-info/METADATA
rain_pack_sdk-3.2.12.dist-info/WHEEL
rain_pack_sdk-3.2.12.dist-info/top_level.txt
rain_pack_sdk-3.2.12.dist-info/RECORD
